beatstrike/__init__.py
beatstrike/animation.py
beatstrike/bg_select.py
beatstrike/button.py
beatstrike/char_select.py
beatstrike/fade_out.py
beatstrike/game.py
beatstrike/main.py
beatstrike/menu.py
beatstrike/music_select.py
beatstrike/options.py
beatstrike/player_select.py
beatstrike/renderer.py
beatstrike/score_screen.py
beatstrike/assets/__init__.py
beatstrike/assets/backgrounds/blue city/frame_00_delay-0.13s.png
beatstrike/assets/backgrounds/blue city/frame_01_delay-0.13s.png
beatstrike/assets/backgrounds/blue city/frame_02_delay-0.13s.png
beatstrike/assets/backgrounds/blue city/frame_03_delay-0.13s.png
beatstrike/assets/backgrounds/blue city/frame_04_delay-0.13s.png
beatstrike/assets/backgrounds/blue city/frame_05_delay-0.13s.png
beatstrike/assets/backgrounds/blue city/frame_06_delay-0.13s.png
beatstrike/assets/backgrounds/blue city/frame_07_delay-0.13s.png
beatstrike/assets/backgrounds/blue city/frame_08_delay-0.13s.png
beatstrike/assets/backgrounds/blue city/frame_09_delay-0.13s.png
beatstrike/assets/backgrounds/blue city/frame_10_delay-0.13s.png
beatstrike/assets/backgrounds/blue city/frame_11_delay-0.13s.png
beatstrike/assets/backgrounds/blue city/frame_12_delay-0.13s.png
beatstrike/assets/backgrounds/blue city/frame_13_delay-0.13s.png
beatstrike/assets/backgrounds/blue city/frame_14_delay-0.13s.png
beatstrike/assets/backgrounds/blue city/frame_15_delay-0.13s.png
beatstrike/assets/backgrounds/blue city/frame_16_delay-0.13s.png
beatstrike/assets/backgrounds/blue city/frame_17_delay-0.13s.png
beatstrike/assets/backgrounds/blue city/frame_18_delay-0.13s.png
beatstrike/assets/backgrounds/blue city/frame_19_delay-0.13s.png
beatstrike/assets/backgrounds/blue city/frame_20_delay-0.13s.png
beatstrike/assets/backgrounds/blue city/frame_21_delay-0.13s.png
beatstrike/assets/backgrounds/blue city/frame_22_delay-0.13s.png
beatstrike/assets/backgrounds/blue city/frame_23_delay-0.13s.png
beatstrike/assets/backgrounds/blue city/frame_24_delay-0.13s.png
beatstrike-0.1.2.dist-info/METADATA
beatstrike-0.1.2.dist-info/WHEEL
beatstrike-0.1.2.dist-info/entry_points.txt
beatstrike-0.1.2.dist-info/top_level.txt
beatstrike-0.1.2.dist-info/RECORD
