Metadata-Version: 2.4
Name: beatstrike
Version: 0.1.2
Summary: Um jogo de ritmo inspirado em Guitar Hero e StepMania
Author-email: Francisco Wedson <wedson.business@gmail.com>
Requires-Python: >=3.11
Requires-Dist: pygame>=2.6.1
